[
	{
		"codigo": 130,
		"descripcion": "Administración General de la Seguridad y Protección Civil."
	},
	{
		"codigo": 132,
		"descripcion": "Seguridad y Orden Público."
	},
	{
		"codigo": 133,
		"descripcion": "Ordenación del tráfico y del estacionamiento."
	},
	{
		"codigo": 134,
		"descripcion": "Protección civil."
	},
	{
		"codigo": 135,
		"descripcion": "Servicio de extinción de incendios."
	},
	{
		"codigo": 150,
		"descripcion": "Administración General de Vivienda y urbanismo."
	},
	{
		"codigo": 151,
		"descripcion": "Urbanismo."
	},
	{
		"codigo": 152,
		"descripcion": "Vivienda."
	},
	{
		"codigo": 153,
		"descripcion": "Acceso a la vivienda."
	},
	{
		"codigo": 154,
		"descripcion": "Fomento de la edificación protegida."
	},
	{
		"codigo": 155,
		"descripcion": "Vías públicas."
	},
	{
		"codigo": 160,
		"descripcion": "Alcantarillado."
	},
	{
		"codigo": 161,
		"descripcion": "Saneamiento, abastecimiento y distribución de aguas."
	},
	{
		"codigo": 162,
		"descripcion": "Recogida, eliminación y tratamiento de residuos."
	},
	{
		"codigo": 163,
		"descripcion": "Limpieza viaria."
	},
	{
		"codigo": 164,
		"descripcion": "Cementerio y servicios funerarios."
	},
	{
		"codigo": 165,
		"descripcion": "Alumbrado público."
	},
	{
		"codigo": 169,
		"descripcion": "Otros servicios de bienestar comunitario."
	},
	{
		"codigo": 170,
		"descripcion": "Administración general del medio ambiente."
	},
	{
		"codigo": 171,
		"descripcion": "Parques y jardines."
	},
	{
		"codigo": 172,
		"descripcion": "Protección y mejora del medio ambiente."
	},
	{
		"codigo": 179,
		"descripcion": "Otras actuaciones relacionadas con el medio ambiente."
	},
	{
		"codigo": 211,
		"descripcion": "Pensiones."
	},
	{
		"codigo": 221,
		"descripcion": "Otras prestaciones económicas a favor de empleados."
	},
	{
		"codigo": 230,
		"descripcion": "Administración General de servicios sociales."
	},
	{
		"codigo": 231,
		"descripcion": "Acción social."
	},
	{
		"codigo": 232,
		"descripcion": "Promoción social."
	},
	{
		"codigo": 233,
		"descripcion": "Asistencia a personas dependientes."
	},
	{
		"codigo": 241,
		"descripcion": "Fomento del Empleo."
	},
	{
		"codigo": 311,
		"descripcion": "Protección de la salubridad pública."
	},
	{
		"codigo": 312,
		"descripcion": "Hospitales, servicios asistenciales y centros de salud."
	},
	{
		"codigo": 313,
		"descripcion": "Acciones públicas relativas a la salud."
	},
	{
		"codigo": 320,
		"descripcion": "Administración general de educación."
	},
	{
		"codigo": 321,
		"descripcion": "Creación de Centros docentes de enseñanza preescolar y primaria."
	},
	{
		"codigo": 322,
		"descripcion": "Creación de Centros docentes de enseñanza secundaria."
	},
	{
		"codigo": 323,
		"descripcion": "Funcionamiento de centros docentes de enseñanza preescolar y primaria y educación especial"
	},
	{
		"codigo": 324,
		"descripcion": "Funcionamiento de centros docentes de enseñanza secundaria."
	},
	{
		"codigo": 326,
		"descripcion": "Servicios complementarios de educación."
	},
	{
		"codigo": 327,
		"descripcion": "Fomento de la convivencia ciudadana."
	},
	{
		"codigo": 330,
		"descripcion": "Administración General de Cultura."
	},
	{
		"codigo": 332,
		"descripcion": "Bibliotecas y Archivos."
	},
	{
		"codigo": 333,
		"descripcion": "Museos y Artes Plásticas."
	},
	{
		"codigo": 334,
		"descripcion": "Promoción cultural."
	},
	{
		"codigo": 335,
		"descripcion": "Artes escénicas."
	},
	{
		"codigo": 336,
		"descripcion": "Arqueología y protección del Patrimonio Histórico-Artístico."
	},
	{
		"codigo": 337,
		"descripcion": "Ocio y tiempo libre"
	},
	{
		"codigo": 338,
		"descripcion": "Fiestas populares y festejos."
	},
	{
		"codigo": 340,
		"descripcion": "Administración General de Deportes."
	},
	{
		"codigo": 341,
		"descripcion": "Promoción y fomento del deporte."
	},
	{
		"codigo": 342,
		"descripcion": "Instalaciones deportivas."
	},
	{
		"codigo": 410,
		"descripcion": "Administración General de Agricultura, Ganadería y Pesca."
	},
	{
		"codigo": 412,
		"descripcion": "Mejora de las estructuras agropecuarias y de los sistemas productivos."
	},
	{
		"codigo": 414,
		"descripcion": "Desarrollo rural."
	},
	{
		"codigo": 415,
		"descripcion": "Protección y desarrollo de los recursos pesqueros."
	},
	{
		"codigo": 419,
		"descripcion": "Otras actuaciones en agricultura, ganadería y pesca."
	},
	{
		"codigo": 420,
		"descripcion": "Administración General de Industria y energía."
	},
	{
		"codigo": 422,
		"descripcion": "Industria."
	},
	{
		"codigo": 423,
		"descripcion": "Minería."
	},
	{
		"codigo": 425,
		"descripcion": "Energía."
	},
	{
		"codigo": 430,
		"descripcion": "Administración General de Comercio, turismo y pequeñas y medianas empresas."
	},
	{
		"codigo": 431,
		"descripcion": "Comercio."
	},
	{
		"codigo": 432,
		"descripcion": "Ordenación y promoción turística."
	},
	{
		"codigo": 433,
		"descripcion": "Desarrollo empresarial."
	},
	{
		"codigo": 439,
		"descripcion": "Otras actuaciones sectoriales."
	},
	{
		"codigo": 440,
		"descripcion": "Administración general del transporte."
	},
	{
		"codigo": 441,
		"descripcion": "Promoción, mantenimiento y desarrollo del transporte."
	},
	{
		"codigo": 442,
		"descripcion": "Infraestructuras del transporte."
	},
	{
		"codigo": 450,
		"descripcion": "Administración General de Infraestructuras."
	},
	{
		"codigo": 452,
		"descripcion": "Recursos Hidráulicos."
	},
	{
		"codigo": 453,
		"descripcion": "Carreteras ."
	},
	{
		"codigo": 454,
		"descripcion": "Caminos vecinales."
	},
	{
		"codigo": 459,
		"descripcion": "Otras infraestructuras."
	},
	{
		"codigo": 462,
		"descripcion": "Investigación y estudios relacionados con los servicios públicos."
	},
	{
		"codigo": 463,
		"descripcion": "Investigación científica, técnica y aplicada."
	},
	{
		"codigo": 491,
		"descripcion": "Sociedad de la información."
	},
	{
		"codigo": 492,
		"descripcion": "Gestión del conocimiento."
	},
	{
		"codigo": 493,
		"descripcion": "Oficinas de defensa al consumidor."
	},
	{
		"codigo": 912,
		"descripcion": "Órganos de gobierno."
	},
	{
		"codigo": 920,
		"descripcion": "Administración General."
	},
	{
		"codigo": 922,
		"descripcion": "Coordinación y organización institucional de las entidades locales."
	},
	{
		"codigo": 923,
		"descripcion": "Información básica y estadística."
	},
	{
		"codigo": 924,
		"descripcion": "Participación ciudadana."
	},
	{
		"codigo": 925,
		"descripcion": "Atención a los ciudadanos."
	},
	{
		"codigo": 926,
		"descripcion": "Comunicaciones internas."
	},
	{
		"codigo": 929,
		"descripcion": "Imprevistos y funciones no clasificadas."
	},
	{
		"codigo": 931,
		"descripcion": "Política económica y fiscal."
	},
	{
		"codigo": 932,
		"descripcion": "Gestión del sistema tributario."
	},
	{
		"codigo": 933,
		"descripcion": "Gestión del patrimonio."
	},
	{
		"codigo": 934,
		"descripcion": "Gestión de la deuda y de la tesorería."
	},
	{
		"codigo": 941,
		"descripcion": "Transferencias a Comunidades Autónomas."
	},
	{
		"codigo": 942,
		"descripcion": "Transferencias a Entidades Locales territoriales."
	},
	{
		"codigo": 943,
		"descripcion": "Transferencias a otras Entidades Locales."
	},
	{
		"codigo": 944,
		"descripcion": "Transferencias a la Administración General del Estado."
	},
	{
		"codigo": 11,
		"descripcion": "Deuda Pública."
	}
]
