[
	{
		"data": "Expediente",
		"value": "",
		"URL": ""
	},
	{
		"data": "Descripción",
		"value": "Remodelación de la plaza del Mercado"
	},
	{
		"data": "Estado",
		"value": "Presentación de propuestas"
	},
	{
		"data": "Procedimiento",
		"value": ""
	},
	{
		"data": "Tipo contrato",
		"value": ""
	},
	{
		"data": "Fecha final licitación",
		"value": ""
	},
	{
		"data": "Fecha Formalización",
		"value": ""
	},
	{
		"data": "Presupuesto base de licitación sin impuestos",
		"value": ""
	},
	{
		"data": "Valor estimado del contrato",
		"value": ""
	},
	{
		"data": "Licitadores presentados",
		"value": ""
	},
	{
		"data": "Adjudicatario",
		"value": ""
	},
	{
		"data": "CIF Adjudicatario",
		"value": ""
	},
	{
		"data": "Información sobre el adjudicatario",
		"value": "Pulsar en enlace para ver la información",
		"URL": ""
	},
	{
		"data": "Importe de Adjudicación",
		"value": ""
	},
	{
		"data": "Financiación",
		"value": "Fondos Next Generation EU"
	},
	{
		"data": "Plazo máximo por financiación",
		"value": "31 mayo 2025"
	},
	{
		"data": "Credito en que se ampara",
		"value": ""
	},
	{
		"data": "Organico",
		"value": ""
	},
	{
		"data": "Programa",
		"value": ""
	},
	{
		"data": "Económico",
		"value": ""
	},
	{
		"data": "Plazo ejecución",
		"value": ""
	},
	{
		"data": "Geolocalización",
		"value": "Pulsar en el enlace para ver la ubicación",
		"URL": "https://goo.gl/maps/iH7Qu6cggkfmbuv36"
	},
	{
		"data": "Distrito",
		"value": "Centro (Pulsar en el enlace para ver el contorno del distrito)",
		"URL": "https://www.google.com/maps/d/viewer?mid=18pN3Nn98Ij37DHMPQFRIbF30pV0&femb=1&ll=36.68446675434557%2C-6.136462500000008&z=16"
	}
]
