[
	{
		"title": "Presupuestos",
		"path": "presupuestos",
		"isLastLevel": true,
		"rutaImagen": "assets/img/home/menu1-400x250.webp"
	},
	{
		"title": "Deuda",
		"path": "/deuda",
		"isLastLevel": true,
		"rutaImagen": "assets/deuda/deuda.jpg"
	},
	{
		"title": "PMP",
		"path": "art16/pmp",
		"isLastLevel": true,
		"rutaImagen": "assets/art16/pmp/2023-09.jpg"
	},
	{
		"title": "Impuestos",
		"path": "art16/impuestos",
		"isLastLevel": true,
		"rutaImagen": "assets/art16/impuestos/impuestos.jpg"
	}
]
