[
	{
		"title": "Edificios singulares",
		"path": "edificiosSingulares",
		"isLastLevel": false,
		"tag": "palacioRiquelme"
	},
	{
		"title": "Apartamentos turísticos",
		"path": "medioambiental/apartamentosTuristicos",
		"isLastLevel": true,
		"tag": "apartamentosTuristicos"
	},
	{
		"title": "Proyectos construcción de viviendas",
		"path": "medioambiental/proyectosViviendas",
		"isLastLevel": true,
		"tag": "proyectosViviendas"
	},
	{
		"title": "Poligonos industriales",
		"path": "medioambiental/poligonosIndustriales",
		"isLastLevel": true,
		"tag": "poligonosIndustriales"
	},
	{
		"title": "Registro solares y edificaciones ruinosas",
		"path": "medioambiental/registroSolares",
		"isLastLevel": true,
		"tag": "registroSolares"
	},
	{
		"title": "Mercados",
		"path": "medioambiental/mercados",
		"isLastLevel": true,
		"tag": "mercados"
	},
	{
		"title": "Patrimonio Histórico",
		"path": "medioambiental/patrimonioHistorico",
		"isLastLevel": true,
		"tag": "patrimonioHistorico"
	}
]