[
	{
		"data": "Expediente",
		"value": "ASUECO 2023/1731",
		"URL": "https://contrataciondelestado.es/wps/poc?uri=deeplink%3Adetalle_licitacion&idEvl=0RFOekcKdhPXOjazN1Dw9Q%3D%3D"
	},
	{
		"data": "Descripción",
		"value": "Proyecto básico y de ejecución de actuaciones necesarias de reparación y conservación en la Torre de la Atalaya y Documento de Adenda al mismo."
	},
	{
		"data": "Procedimiento",
		"value": "Abierto simplificado"
	},
	{
		"data": "Tipo contrato",
		"value": "Obras"
	},
	{
		"data": "Valor estimado del contrato",
		"value": "67.669,36"
	},
	{
		"data": "Licitadores presentados",
		"value": "2"
	},
	{
		"data": "Adjudicatario",
		"value": ""
	},
	{
		"data": "CIF Adjudicatario",
		"value": ""
	},
	{
		"data": "Información sobre el adjudicatario",
		"value": "Pulsar en enlace para ver la información",
		"URL": ""
	},
	{
		"data": "Importe de Adjudicación",
		"value": ""
	},
	{
		"data": "Financiación",
		"value": "Subvención diputación Provincial de Cádiz"
	},
	{
		"data": "Credito en que se ampara",
		"value": ""
	},
	{
		"data": "Organico",
		"value": ""
	},
	{
		"data": "Programa",
		"value": ""
	},
	{
		"data": "Económico",
		"value": ""
	},
	{
		"data": "Plazo ejecución",
		"value": "5 meses"
	},
	{
		"data": "Geolocalización",
		"value": "Pulsar en el enlace para ver la ubicación",
		"URL": "https://maps.app.goo.gl/CBoQMEmZUvzHUzGC8"
	},
	{
		"data": "Distrito",
		"value": "Centro (Pulsar en el enlace para ver el contorno del distrito)",
		"URL": "https://www.google.com/maps/d/viewer?msa=0&ie=UTF8&ll=36.68446675434557%2C-6.136462000000007&spn=0.021544%2C0.025475&t=h&source=embed&mid=18pN3Nn98Ij37DHMPQFRIbF30pV0&z=16"
	}
]
