[
	{
		"date": "12 diciembre 2023",
		"medio": "Diario de Jerez",
		"title": "El Ayuntamiento de Jerez instalará espacios de sombra, zonas verdes y arbolado en Plaza Belén",
		"URL": "https://www.diariodejerez.es/jerez/Ayuntamiento-Jerez-instalara-espacios-sombra-Plaza-Belen_0_1856215147.html"
	},

	{
		"date": "12 diciembre 2023",
		"medio": "Diario de Jerez",
		"title": "",
		"URL": ""
	},
	{
		"date": "5 diciembre 2023",
		"medio": "La Voz del Sur",
		"title": "",
		"URL": ""
	},
	{
		"date": "17 noviembre 2023",
		"medio": "Viva Jerez",
		"title": "",
		"URL": ""
	},
	{
		"date": "1 diciembre 2023",
		"medio": "El Mira Jerez",
		"title": "",
		"URL": ""
	}
]
