[
	{
		"date": "20 diciembre 2023",
		"medio": "El Mira Jerez",
		"title": "Francisco Zuasti adquiere un edificio histórico para promover el turismo accesible en Jerez",
		"URL": "https://www.elmira.es/articulo/jerez/francisco-zuasti-adquiere-edificio-historico-promover-turismo-accesible-jerez/20231220100909430989.html"
	},

	{
		"date": "20 diciembre 2023",
		"medio": "Diario de Jerez",
		"title": "",
		"URL": ""
	},
	{
		"date": "5 diciembre 2023",
		"medio": "La Voz del Sur",
		"title": "",
		"URL": ""
	},
	{
		"date": "17 noviembre 2023",
		"medio": "Viva Jerez",
		"title": "",
		"URL": ""
	},
	{
		"date": "1 diciembre 2023",
		"medio": "El Mira Jerez",
		"title": "",
		"URL": ""
	}
]
